[
	{
		"__TYPE__": "SharedSliceContent",
		"variation": "default",
		"primary": {
			"heading": {
				"__TYPE__": "StructuredTextContent",
				"value": [
					{
						"type": "heading1",
						"content": {
							"text": "SkyPoint Breakfast Buffet",
							"spans": []
						},
						"direction": "ltr"
					}
				]
			},
			"body": {
				"__TYPE__": "StructuredTextContent",
				"value": [
					{
						"type": "paragraph",
						"content": {
							"text": "It's the only way to start your day. Enjoy SkyPoint's Breakfast Buffet every day between 7:30am - 10:30am. Tickets from $28 for kids.",
							"spans": []
						},
						"direction": "ltr"
					}
				]
			},
			"button_text": {
				"__TYPE__": "FieldContent",
				"type": "Text",
				"value": "Learn More"
			},
			"button_link": {
				"__TYPE__": "LinkContent",
				"value": {
					"__TYPE__": "ExternalLink",
					"url": "https://prismic.io"
				}
			},
			"image": {
				"origin": {
					"id": "N_Y88TWmGwA",
					"url": "https://images.unsplash.com/photo-1414235077428-338989a2e8c0?crop=entropy&cs=srgb&fm=jpg&ixid=M3wzMzc0NjN8MHwxfHNlYXJjaHwyNnx8Zm9vZHxlbnwwfHx8fDE2OTQ2NTYxMzF8MA&ixlib=rb-4.0.3&q=85",
					"width": 4402,
					"height": 2935
				},
				"url": "https://images.unsplash.com/photo-1414235077428-338989a2e8c0?crop=entropy&cs=srgb&fm=jpg&ixid=M3wzMzc0NjN8MHwxfHNlYXJjaHwyNnx8Zm9vZHxlbnwwfHx8fDE2OTQ2NTYxMzF8MA&ixlib=rb-4.0.3&q=85",
				"width": 4402,
				"height": 2935,
				"edit": {
					"background": "transparent",
					"zoom": 1,
					"crop": {
						"x": 0,
						"y": 0
					}
				},
				"credits": null,
				"alt": null,
				"__TYPE__": "ImageContent",
				"thumbnails": {}
			}
		},
		"items": []
	},
	{
		"__TYPE__": "SharedSliceContent",
		"variation": "horizontal",
		"primary": {
			"heading": {
				"__TYPE__": "StructuredTextContent",
				"value": [
					{
						"type": "heading1",
						"content": {
							"text": "From day sights, to city lights",
							"spans": []
						},
						"direction": "ltr"
					}
				]
			},
			"body": {
				"__TYPE__": "StructuredTextContent",
				"value": [
					{
						"type": "paragraph",
						"content": {
							"text": "SkyPoint is now open until 9pm, meaning that you can enjoy our stunning views all day, right through sunset and into the evening as the Gold Coast bursts to life with city lights and an explosion of colour! SkyPoint Bistro + Bar is open into the evening as well, so you can enjoy after work drinks, or dinner with the best view in town.",
							"spans": []
						},
						"direction": "ltr"
					}
				]
			},
			"button_text": {
				"__TYPE__": "FieldContent",
				"type": "Text",
				"value": "Opening Hours"
			},
			"button_link": {
				"__TYPE__": "LinkContent",
				"value": {
					"__TYPE__": "ExternalLink",
					"url": "https://prismic.io"
				}
			},
			"image": {
				"origin": {
					"id": "2sC_EnA5Fbk",
					"url": "https://images.unsplash.com/photo-1566100209935-71f9aa99d69b?crop=entropy&cs=srgb&fm=jpg&ixid=M3wzMzc0NjN8MHwxfHNlYXJjaHwxfHxza3lwb2ludHxlbnwwfHx8fDE2OTQ2NTU4NTh8MA&ixlib=rb-4.0.3&q=85",
					"width": 5504,
					"height": 6880
				},
				"url": "https://images.unsplash.com/photo-1566100209935-71f9aa99d69b?crop=entropy&cs=srgb&fm=jpg&ixid=M3wzMzc0NjN8MHwxfHNlYXJjaHwxfHxza3lwb2ludHxlbnwwfHx8fDE2OTQ2NTU4NTh8MA&ixlib=rb-4.0.3&q=85&rect=743%2C929%2C4018%2C5022&w=5504&h=6880",
				"width": 5504,
				"height": 6880,
				"edit": {
					"background": "transparent",
					"zoom": 1.37,
					"crop": {
						"x": 743,
						"y": 929
					}
				},
				"credits": null,
				"alt": null,
				"__TYPE__": "ImageContent",
				"thumbnails": {}
			}
		},
		"items": [
			{
				"__TYPE__": "GroupItemContent",
				"value": []
			}
		]
	},
	{
		"__TYPE__": "SharedSliceContent",
		"variation": "horizontalLeftImage",
		"primary": {
			"heading": {
				"__TYPE__": "StructuredTextContent",
				"value": [
					{
						"type": "heading1",
						"content": {
							"text": "SkyPoint",
							"spans": []
						},
						"direction": "ltr"
					}
				]
			},
			"body": {
				"__TYPE__": "StructuredTextContent",
				"value": [
					{
						"type": "paragraph",
						"content": {
							"text": "SkyPoint is now open until 9pm, meaning that you can enjoy our stunning views all day, right through sunset and into the evening as the Gold Coast bursts to life with city lights and an explosion of colour! SkyPoint Bistro + Bar is open into the evening as well, so you can enjoy after work drinks, or dinner with the best view in town.",
							"spans": []
						},
						"direction": "ltr"
					}
				]
			},
			"image": {
				"origin": {
					"id": "2sC_EnA5Fbk",
					"url": "https://images.unsplash.com/photo-1566100209935-71f9aa99d69b?crop=entropy&cs=srgb&fm=jpg&ixid=M3wzMzc0NjN8MHwxfHNlYXJjaHwxfHxza3lwb2ludHxlbnwwfHx8fDE2OTQ2NTU4NTh8MA&ixlib=rb-4.0.3&q=85",
					"width": 5504,
					"height": 6880
				},
				"url": "https://images.unsplash.com/photo-1566100209935-71f9aa99d69b?crop=entropy&cs=srgb&fm=jpg&ixid=M3wzMzc0NjN8MHwxfHNlYXJjaHwxfHxza3lwb2ludHxlbnwwfHx8fDE2OTQ2NTU4NTh8MA&ixlib=rb-4.0.3&q=85",
				"width": 5504,
				"height": 6880,
				"edit": {
					"background": "transparent",
					"zoom": 1,
					"crop": {
						"x": 0,
						"y": 0
					}
				},
				"credits": null,
				"__TYPE__": "ImageContent",
				"thumbnails": {}
			},
			"button_text": {
				"__TYPE__": "FieldContent",
				"type": "Text",
				"value": "Buy Ticket"
			},
			"button_link": {
				"__TYPE__": "LinkContent",
				"value": {
					"__TYPE__": "ExternalLink",
					"url": "https://skypoint.com.au/dine/"
				}
			}
		},
		"items": [
			{
				"__TYPE__": "GroupItemContent",
				"value": []
			}
		]
	}
]